minty_infra_amqp/__init__.py
minty_infra_amqp/py.typed
minty_infra_amqp-2.0.1.dist-info/LICENSE
minty_infra_amqp-2.0.1.dist-info/METADATA
minty_infra_amqp-2.0.1.dist-info/WHEEL
minty_infra_amqp-2.0.1.dist-info/top_level.txt
minty_infra_amqp-2.0.1.dist-info/RECORD
