Metadata-Version: 2.1
Name: minty-infra-amqp
Version: 2.0.1
Summary: AMQP infrastructure for the Minty system
Home-page: https://gitlab.com/minty-python/minty-infra-amqp
Author: Martijn van de Streek
Author-email: martijn@mintlab.nl
License: EUPL license
Keywords: minty_infra_amqp
Platform: UNKNOWN
Classifier: Development Status :: 2 - Pre-Alpha
Classifier: Intended Audience :: Developers
Classifier: License :: OSI Approved :: European Union Public Licence 1.2 (EUPL 1.2)
Classifier: Natural Language :: English
Classifier: Programming Language :: Python :: 3.6
Classifier: Programming Language :: Python :: 3.7
License-File: LICENSE
Requires-Dist: minty (~=3.0)
Requires-Dist: amqpstorm (~=2.8)
